conftest.py
moocore/_moocore.py
moocore/_datasets.py
moocore/__init__.py
moocore/_ffi_build.py
moocore/_utils.py
moocore/libmoocore.h
moocore/_libmoocore.abi3.so
moocore/libmoocore/avl.c
moocore/libmoocore/epsilon.c
moocore/libmoocore/nondominated.c
moocore/libmoocore/timer.c
moocore/libmoocore/main-hvapprox.c
moocore/libmoocore/eafdiff.c
moocore/libmoocore/hv4d_priv.h
moocore/libmoocore/hv_contrib.c
moocore/libmoocore/main-hv.c
moocore/libmoocore/config.h
moocore/libmoocore/io.c
moocore/libmoocore/libutil.c
moocore/libmoocore/gcc_attribs.h
moocore/libmoocore/avl_tiny.h
moocore/libmoocore/hvapprox.h
moocore/libmoocore/eaf.c
moocore/libmoocore/cmdline.h
moocore/libmoocore/cvector.h
moocore/libmoocore/io_priv.h
moocore/libmoocore/whv.c
moocore/libmoocore/whv_hype.c
moocore/libmoocore/rng.h
moocore/libmoocore/igd.h
moocore/libmoocore/hv4d.c
moocore/libmoocore/hv.h
moocore/libmoocore/timer.h
moocore/libmoocore/nondominated.h
moocore/libmoocore/pareto.c
moocore/libmoocore/epsilon.h
moocore/libmoocore/common.h
moocore/libmoocore/dominatedsets.c
moocore/libmoocore/eaf3d.c
moocore/libmoocore/avl.h
moocore/libmoocore/hv3dplus.c
moocore/libmoocore/io.h
moocore/libmoocore/ziggurat_constants.h
moocore/libmoocore/bit_array.h
moocore/libmoocore/hv3d_priv.h
moocore/libmoocore/hvc3d.c
moocore/libmoocore/cmdline.c
moocore/libmoocore/hv_priv.h
moocore/libmoocore/maxminclamp.h
moocore/libmoocore/eaf.h
moocore/libmoocore/sort.h
moocore/libmoocore/hvapprox.c
moocore/libmoocore/libmoocore-config.h
moocore/libmoocore/pow_int.h
moocore/libmoocore/hv.c
moocore/libmoocore/eaf_main.c
moocore/libmoocore/igd.c
moocore/libmoocore/rng.c
moocore/libmoocore/ndsort.c
moocore/libmoocore/whv_hype.h
moocore/libmoocore/whv.h
moocore/libmoocore/mt19937/mt19937.c
moocore/libmoocore/mt19937/mt19937.h
moocore/data/input1.dat
moocore/data/ran.10pts.9d.10
moocore/data/wrots_l100w10_dat.xz
moocore/data/tpls50x20_1_MWT.csv
moocore-0.2.0.dist-info/RECORD
moocore-0.2.0.dist-info/WHEEL
moocore-0.2.0.dist-info/top_level.txt
moocore-0.2.0.dist-info/METADATA
moocore-0.2.0.dist-info/licenses/COPYRIGHTS
