Metadata-Version: 2.4
Name: moocore
Version: 0.2.0
Summary: Core Algorithms for Multi-Objective Optimization
Author-email: Manuel López-Ibáñez <manuel.lopez-ibanez@manchester.ac.uk>, Fergus Rooney <fergus.rooney@outlook.com>
License-Expression: LGPL-2.1-or-later
Project-URL: Documentation, https://multi-objective.github.io/moocore/python/
Project-URL: Homepage, https://multi-objective.github.io/moocore/python/
Project-URL: Source, https://github.com/multi-objective/moocore/
Project-URL: Tracker, https://github.com/multi-objective/moocore/issues
Keywords: math,Mathematics,Multi-criteria Decision-Making,operations research,Optimization
Classifier: Intended Audience :: Science/Research
Classifier: Operating System :: OS Independent
Classifier: Programming Language :: Python :: 3 :: Only
Classifier: Programming Language :: Python :: 3.10
Classifier: Programming Language :: Python :: 3.11
Classifier: Programming Language :: Python :: 3.12
Classifier: Programming Language :: Python :: 3.13
Classifier: Programming Language :: Python :: 3.14
Requires-Python: >=3.10
License-File: COPYRIGHTS
Requires-Dist: cffi>=1.17.1
Requires-Dist: numpy>=1.24
Requires-Dist: platformdirs
Provides-Extra: benchmarks
Requires-Dist: botorch; extra == "benchmarks"
Requires-Dist: desdeo; extra == "benchmarks"
Requires-Dist: fast-pareto; extra == "benchmarks"
Requires-Dist: jmetalpy; extra == "benchmarks"
Requires-Dist: matplotlib; extra == "benchmarks"
Requires-Dist: nevergrad; extra == "benchmarks"
Requires-Dist: numba; extra == "benchmarks"
Requires-Dist: numpy; extra == "benchmarks"
Requires-Dist: optuna; extra == "benchmarks"
Requires-Dist: pandas>=2; extra == "benchmarks"
Requires-Dist: paretoset; extra == "benchmarks"
Requires-Dist: py-cpuinfo; extra == "benchmarks"
Requires-Dist: pymoo; extra == "benchmarks"
Requires-Dist: seqme; extra == "benchmarks"
Provides-Extra: coverage
Requires-Dist: coverage[toml]; extra == "coverage"
Requires-Dist: gcovr; extra == "coverage"
Provides-Extra: dev
Requires-Dist: pre-commit>=3.3.2; extra == "dev"
Requires-Dist: ruff>=0.11.2; extra == "dev"
Requires-Dist: tox>=4.6.2; extra == "dev"
Provides-Extra: docs
Requires-Dist: ipykernel; extra == "docs"
Requires-Dist: ipywidgets; extra == "docs"
Requires-Dist: jupyter; extra == "docs"
Requires-Dist: jupyterlab; extra == "docs"
Requires-Dist: kaleido; extra == "docs"
Requires-Dist: pandas>=2; extra == "docs"
Requires-Dist: plotly; extra == "docs"
Requires-Dist: pydata-sphinx-theme>=0.16; extra == "docs"
Requires-Dist: seaborn; extra == "docs"
Requires-Dist: sphinx>=6; extra == "docs"
Requires-Dist: sphinx-autodoc-typehints; extra == "docs"
Requires-Dist: sphinx-copybutton; extra == "docs"
Requires-Dist: sphinx-design; extra == "docs"
Requires-Dist: sphinx-gallery>=0.19; extra == "docs"
Requires-Dist: sphinxcontrib-bibtex; extra == "docs"
Requires-Dist: sphinxcontrib-napoleon; extra == "docs"
Provides-Extra: test
Requires-Dist: pandas>=2; extra == "test"
Requires-Dist: pytest>7; extra == "test"
Dynamic: license-file
